combpyter/__init__.py
combpyter/lattice_paths/__init__.py
combpyter/lattice_paths/dyck_paths.py
combpyter-0.0.6.dist-info/METADATA
combpyter-0.0.6.dist-info/WHEEL
combpyter-0.0.6.dist-info/licenses/LICENSE
combpyter-0.0.6.dist-info/RECORD
