Metadata-Version: 2.4
Name: combpyter
Version: 0.0.6
Summary: A lightweight Python library for generating and analyzing combinatorial objects.
Project-URL: repository, https://github.com/behackl/combpyter
Author-email: Benjamin Hackl <devel@benjamin-hackl.at>
License: MIT
License-File: LICENSE
Requires-Python: <4.0,>=3.10
Requires-Dist: matplotlib[plot]>=3.5.1
Requires-Dist: numpy>=2.0.0
